kaggle_blocks/__init__.py
kaggle_blocks/_modidx.py
kaggle_blocks/utils/__init__.py
kaggle_blocks/utils/utils.py
kaggle_blocks-0.0.1.dist-info/LICENSE
kaggle_blocks-0.0.1.dist-info/METADATA
kaggle_blocks-0.0.1.dist-info/WHEEL
kaggle_blocks-0.0.1.dist-info/entry_points.txt
kaggle_blocks-0.0.1.dist-info/top_level.txt
kaggle_blocks-0.0.1.dist-info/RECORD
