Metadata-Version: 2.1
Name: kaggle-blocks
Version: 0.0.1
Summary: Reusable and modular blocks for kaggle competitions
Home-page: https://github.com/JaumeAmores/kaggle-blocks
Author: Jaume Amores
Author-email: jaumeamllo77@gmail.com
License: Apache Software License 2.0
Keywords: nbdev jupyter notebook python
Platform: UNKNOWN
Classifier: Development Status :: 4 - Beta
Classifier: Intended Audience :: Developers
Classifier: Natural Language :: English
Classifier: Programming Language :: Python :: 3.7
Classifier: Programming Language :: Python :: 3.8
Classifier: Programming Language :: Python :: 3.9
Classifier: Programming Language :: Python :: 3.10
Classifier: License :: OSI Approved :: Apache Software License
Requires-Python: >=3.7
License-File: LICENSE
Requires-Dist: dsblocks
Requires-Dist: kaggle
Requires-Dist: datasets
Requires-Dist: transformers
Requires-Dist: sentencepiece
Requires-Dist: torch
Provides-Extra: dev
